kapt_apidae/__init__.py
kapt_apidae/admin.py
kapt_apidae/apps.py
kapt_apidae/cms_toolbars.py
kapt_apidae/conf/__init__.py
kapt_apidae/conf/settings.py
kapt_apidae/core/__init__.py
kapt_apidae/core/db/__init__.py
kapt_apidae/core/db/choices.py
kapt_apidae/core/exceptions.py
kapt_apidae/core/toolbar/items.py
kapt_apidae/locale/fr/LC_MESSAGES/django.mo
kapt_apidae/locale/fr/LC_MESSAGES/django.po
kapt_apidae/management/__init__.py
kapt_apidae/management/commands/__init__.py
kapt_apidae/management/commands/import_apidae.py
kapt_apidae/management/commands/import_apidae_kaptravel.py
kapt_apidae/management/commands/import_apidae_to_kapt_travel/__init__.py
kapt_apidae/management/commands/import_apidae_to_kapt_travel/associative_life/__init__.py
kapt_apidae/management/commands/import_apidae_to_kapt_travel/associative_life/member.py
kapt_apidae/management/commands/import_apidae_to_kapt_travel/catalog/__init__.py
kapt_apidae/management/commands/import_apidae_to_kapt_travel/catalog/activities/__init__.py
kapt_apidae/management/commands/import_apidae_to_kapt_travel/catalog/activities/common.py
kapt_apidae/management/commands/import_apidae_to_kapt_travel/catalog/activities/common_mixins/__init__.py
kapt_apidae/management/commands/import_apidae_to_kapt_travel/catalog/activities/common_mixins/periods/__init__.py
kapt_apidae/management/commands/import_apidae_to_kapt_travel/catalog/activities/common_mixins/periods/mapping.py
kapt_apidae/management/commands/import_apidae_to_kapt_travel/catalog/activities/common_mixins/periods/mixin.py
kapt_apidae/management/commands/import_apidae_to_kapt_travel/catalog/activities/common_mixins/periods/utils.py
kapt_apidae/management/commands/import_apidae_to_kapt_travel/catalog/activities/specific/__init__.py
kapt_apidae/management/commands/import_apidae_to_kapt_travel/catalog/activities/specific/area.py
kapt_apidae/management/commands/import_apidae_to_kapt_travel/catalog/activities/specific/business.py
kapt_apidae-2.6.5.dist-info/METADATA
kapt_apidae-2.6.5.dist-info/WHEEL
kapt_apidae-2.6.5.dist-info/RECORD
